argon2_cffi_bindings-21.2.0.dist-info/LICENSE
argon2_cffi_bindings-21.2.0.dist-info/top_level.txt
argon2_cffi_bindings-21.2.0.dist-info/RECORD
argon2_cffi_bindings-21.2.0.dist-info/WHEEL
argon2_cffi_bindings-21.2.0.dist-info/METADATA
_argon2_cffi_bindings/__init__.py
_argon2_cffi_bindings/_ffi.abi3.so
_argon2_cffi_bindings/_ffi_build.py
