Metadata-Version: 2.1
Name: argon2-cffi-bindings
Version: 21.2.0
Summary: Low-level CFFI bindings for Argon2
Home-page: https://github.com/hynek/argon2-cffi-bindings
Author: Hynek Schlawack
Author-email: hs@ox.cx
Maintainer: Hynek Schlawack
Maintainer-email: hs@ox.cx
License: MIT
Project-URL: Source Code, https://github.com/hynek/argon2-cffi-bindings
Project-URL: Funding, https://github.com/sponsors/hynek
Project-URL: Tidelift, https://tidelift.com/subscription/pkg/pypi-argon2-cffi?utm_source=pypi-argon2-cffi&utm_medium=pypi
Project-URL: Ko-fi, https://ko-fi.com/the_hynek
Keywords: password,hash,hashing,security,bindings,cffi
Platform: UNKNOWN
Classifier: Development Status :: 5 - Production/Stable
Classifier: Intended Audience :: Developers
Classifier: License :: OSI Approved :: MIT License
Classifier: Natural Language :: English
Classifier: Operating System :: MacOS :: MacOS X
Classifier: Operating System :: Microsoft :: Windows
Classifier: Operating System :: POSIX
Classifier: Operating System :: Unix
Classifier: Programming Language :: Python :: 3
Classifier: Programming Language :: Python :: 3.6
Classifier: Programming Language :: Python :: 3.7
Classifier: Programming Language :: Python :: 3.8
Classifier: Programming Language :: Python :: 3.9
Classifier: Programming Language :: Python :: 3.10
Classifier: Programming Language :: Python :: Implementation :: CPython
Classifier: Programming Language :: Python :: Implementation :: PyPy
Classifier: Programming Language :: Python
Classifier: Topic :: Security :: Cryptography
Classifier: Topic :: Security
Classifier: Topic :: Software Development :: Libraries :: Python Modules
Requires-Python: >=3.6
Provides-Extra: tests
Provides-Extra: dev
License-File: LICENSE
